README.md
pyrecbot/__init__.py
pyrecbot/record.py
pyrecbot/start.py
pyrecbot-0.1.6.dist-info/METADATA
pyrecbot-0.1.6.dist-info/WHEEL
pyrecbot-0.1.6.dist-info/licenses/LICENSE
pyrecbot-0.1.6.dist-info/RECORD
