Metadata-Version: 2.4
Name: pyrecbot
Version: 0.1.6
Summary: A Python automation module using pynput and pyautogui
Author-email: TDB <terrificdatabytes@gmail.com>
License: MIT License
License-File: LICENSE
Requires-Python: >=3.7
Requires-Dist: pyautogui
Requires-Dist: pynput
